README.md
setup.py
lzm_comtools.egg-info/PKG-INFO
lzm_comtools.egg-info/SOURCES.txt
lzm_comtools.egg-info/dependency_links.txt
lzm_comtools.egg-info/entry_points.txt
lzm_comtools.egg-info/requires.txt
lzm_comtools.egg-info/top_level.txt
src/__init__.py
src/lzm_comtools.py